teppy/__init__.py
teppy/helpers.py
teppy/tep.py
teppy/timefreq.py
teppy-0.1.8.dist-info/LICENSE.txt
teppy-0.1.8.dist-info/METADATA
teppy-0.1.8.dist-info/WHEEL
teppy-0.1.8.dist-info/top_level.txt
teppy-0.1.8.dist-info/RECORD
