Metadata-Version: 2.1
Name: teppy
Version: 0.1.8
Summary: TMS-EEG Evoked Potential Analysis Framework
Project-URL: Homepage, https://github.com/gianlucagag/TEPpy
Classifier: Programming Language :: Python :: 3
Classifier: License :: OSI Approved :: GNU General Public License v3 (GPLv3)
Classifier: Operating System :: OS Independent
Classifier: Intended Audience :: Science/Research
Classifier: Topic :: Scientific/Engineering :: Medical Science Apps.
Requires-Python: >=3.10
License-File: LICENSE.txt
Requires-Dist: numpy>=2.0.1
Requires-Dist: scipy>=1.14.0
Requires-Dist: mne>=1.9.0
Requires-Dist: matplotlib>=3.9.1
Requires-Dist: stockwell>=1.2
